{
  "job_id": "job-018",
  "job_title": "IT Project Manager",
  "company": "RAKBANK",
  "location": "Ras Al Khaimah, UAE",
  "category": "PM",
  "priority": "medium",
  "ats_score": 88,
  "total_keywords": 8,
  "found_keywords": [
    "project management",
    "pmp",
    "agile",
    "ai",
    "banking",
    "core banking",
    "uae"
  ],
  "missing_keywords": [
    "7+ years"
  ],
  "recommendations": [],
  "parsed_jd": {
    "job_title": "IT Project Manager",
    "company": "RAKBANK",
    "location": "Ras Al Khaimah, UAE",
    "salary": null,
    "employment_type": null,
    "requirements": [
      "• 7+ years IT project management",
      "Banking systems experience",
      "PMP certification",
      "Agile methodologies",
      "Vendor coordination"
    ],
    "responsibilities": [
      "7+ years IT project management"
    ],
    "qualifications": [
      "certification • Agile methodologies"
    ],
    "skills": [
      "project management",
      "agile",
      "banking",
      "pmp"
    ],
    "experience_years": null,
    "source": "job-018",
    "parsed_at": "2026-02-11T09:10:57.921Z",
    "raw_text": "IT Project Manager\n\nManage IT projects across digital and core banking systems.\n\nLocation: Ras Al Khaimah, UAE\n\nRequirements:\n• 7+ years IT project management\n• Banking systems experience\n• PMP certification\n• Agile methodologies\n• Vendor coordination",
    "category": "PM",
    "priority": "medium"
  },
  "processed_at": "2026-02-11T09:10:57.922Z"
}