{
  "job_id": "job-014",
  "job_title": "Senior Project Manager",
  "company": "Saudi National Bank",
  "location": "Riyadh, Saudi Arabia",
  "category": "PM",
  "priority": "high",
  "ats_score": 67,
  "total_keywords": 9,
  "found_keywords": [
    "program management",
    "pmp",
    "stakeholder management",
    "banking",
    "arabic",
    "10+ years"
  ],
  "missing_keywords": [
    "vision",
    "saudi",
    "riyadh"
  ],
  "recommendations": [
    "Highlight leadership: vision"
  ],
  "parsed_jd": {
    "job_title": "Senior Project Manager",
    "company": "Saudi National Bank",
    "location": "Riyadh, Saudi Arabia",
    "salary": null,
    "employment_type": null,
    "requirements": [
      "• 10+ years experience",
      "Banking transformation",
      "Program management",
      "Stakeholder management",
      "Arabic language preferred",
      "PMP certification"
    ],
    "responsibilities": [
      "Stakeholder management"
    ],
    "qualifications": [],
    "skills": [
      "stakeholder management",
      "banking",
      "arabic",
      "pmp"
    ],
    "experience_years": "10+",
    "source": "job-014",
    "parsed_at": "2026-02-11T09:10:57.913Z",
    "raw_text": "Senior Project Manager - Vision 2030\n\nLead strategic projects aligned with Saudi Vision 2030 initiatives.\n\nLocation: Riyadh, Saudi Arabia\n\nRequirements:\n• 10+ years experience\n• Banking transformation\n• Program management\n• Stakeholder management\n• Arabic language preferred\n• PMP certification",
    "category": "PM",
    "priority": "high"
  },
  "processed_at": "2026-02-11T09:10:57.913Z"
}